calc/__init__.py
calc/calculator.py
tests/__init__.py
tests/test_Basics.py
CalculatorPackSEDTTT-1.0.3.dist-info/LICENSE
CalculatorPackSEDTTT-1.0.3.dist-info/METADATA
CalculatorPackSEDTTT-1.0.3.dist-info/WHEEL
CalculatorPackSEDTTT-1.0.3.dist-info/top_level.txt
CalculatorPackSEDTTT-1.0.3.dist-info/RECORD
