Metadata-Version: 2.1
Name: CalculatorPackSEDTTT
Version: 1.0.3
Summary: A comprehensive calculator package with various math operations.
Requires-Python: >=3.6
License-File: LICENSE
